sdk/__init__.py
sdk/logger.py
sdk/models.py
sdk/rest.py
sdk/socketio_client.py
socket_sdk-0.dist-info/METADATA
socket_sdk-0.dist-info/WHEEL
socket_sdk-0.dist-info/top_level.txt
socket_sdk-0.dist-info/RECORD
